ocelescope/__init__.py
ocelescope/ocel/__init__.py
ocelescope/ocel/constants.py
ocelescope/ocel/extension.py
ocelescope/ocel/filter/__init__.py
ocelescope/ocel/filter/apply.py
ocelescope/ocel/filter/base.py
ocelescope/ocel/filter/filters/__init__.py
ocelescope/ocel/filter/filters/attribute.py
ocelescope/ocel/filter/filters/entity_type.py
ocelescope/ocel/filter/filters/relation_count.py
ocelescope/ocel/filter/filters/time_range.py
ocelescope/ocel/ocel.py
ocelescope/ocel/util/__init__.py
ocelescope/ocel/util/attributes.py
ocelescope/ocel/util/relations.py
ocelescope/plugin/__init__.py
ocelescope/plugin/decorators.py
ocelescope/plugin/input.py
ocelescope/plugin/plugin.py
ocelescope/resource/__init__.py
ocelescope/resource/default/__init__.py
ocelescope/resource/default/dfg.py
ocelescope/resource/default/petri_net.py
ocelescope/resource/resource.py
ocelescope/tools/build.py
ocelescope/tools/cli.py
ocelescope/util/__init__.py
ocelescope/util/cache.py
ocelescope/util/pandas.py
ocelescope/util/pydantic.py
ocelescope/visualization/__init__.py
ocelescope/visualization/default/__init__.py
ocelescope/visualization/default/dot.py
ocelescope/visualization/default/graph.py
ocelescope/visualization/default/svg.py
ocelescope/visualization/default/table.py
ocelescope/visualization/util/color.py
ocelescope/visualization/visualization.py
ocelescope-0.1.3.dist-info/WHEEL
ocelescope-0.1.3.dist-info/entry_points.txt
ocelescope-0.1.3.dist-info/METADATA
ocelescope-0.1.3.dist-info/RECORD
